subscene2/SubScene.py
subscene2/__init__.py
subscene2/cli.py
subscene2-1.0.2.dist-info/LICENSE
subscene2-1.0.2.dist-info/METADATA
subscene2-1.0.2.dist-info/WHEEL
subscene2-1.0.2.dist-info/entry_points.txt
subscene2-1.0.2.dist-info/top_level.txt
subscene2-1.0.2.dist-info/RECORD
