Metadata-Version: 2.1
Name: subscene2
Version: 1.0.2
Summary: A Python wrapper for SubScene
Home-page: https://github.com/dreygur/subscene-api
Author: Rakibul Yeasin
Author-email: ryeasin03@gmail.com
License: UNKNOWN
Platform: UNKNOWN
Classifier: Programming Language :: Python :: 3
Classifier: License :: OSI Approved :: MIT License
Classifier: Operating System :: OS Independent
Requires-Python: >=3.6
Requires-Dist: beautifulsoup4
Requires-Dist: tqdm (==2.2.3)
